{
    "3": {
        "DDD": 27276,
        "UDD": 20606,
        "DDU": 17206,
        "UUU": 14051,
        "DUU": 13804,
        "UUD": 13710,
        "DUD": 13464,
        "DRD": 11132,
        "DDR": 9356,
        "UDU": 8619,
        "RDR": 7402,
        "WDD": 6058,
        "DDW": 5078,
        "RDU": 5058,
        "DWD": 4813
    },
    "4": {
        "DDDD": 11974,
        "UDDD": 9802,
        "DDDU": 9320,
        "UUDD": 8788,
        "DDUU": 7727,
        "DUDD": 7401,
        "DDUD": 6479,
        "UUUD": 6018,
        "DUUD": 5831,
        "UUUU": 5727,
        "DUUU": 5679,
        "DRDR": 5429,
        "UDDU": 4956,
        "UDDR": 4665,
        "DDRD": 4520
    },
    "5": {
        "DDDDD": 4896,
        "UUDDD": 4877,
        "DDDUU": 4481,
        "UDDDD": 4235,
        "UUUDD": 4161,
        "DDDDU": 4065,
        "DDUDD": 3741,
        "UDDDU": 3578,
        "DDUUU": 3510,
        "DUUDD": 3379,
        "DDDUD": 3010,
        "DRDRD": 2956,
        "DDUUD": 2915,
        "DUDDD": 2888,
        "DUUUD": 2592
    },
    "6": {
        "UUDDDD": 2449,
        "UUUDDD": 2406,
        "DDDUUU": 2204,
        "DDDDUU": 2143,
        "DDDDDD": 1788,
        "DUUUDD": 1771,
        "UDDDDD": 1755,
        "DUUDDD": 1751,
        "UUUUDD": 1725,
        "DDDDDU": 1653,
        "DDDUDD": 1638,
        "UDDDDU": 1633,
        "UDDDUU": 1620,
        "DDDUUD": 1614,
        "DDUUDD": 1567
    },
    "7": {
        "UUUDDDD": 1398,
        "DDDDUUU": 1147,
        "UUDDDDD": 1058,
        "DUUUDDD": 1012,
        "DDUUUDD": 993,
        "UUUUDDD": 992,
        "DDDDDUU": 974,
        "DDDUUUU": 971,
        "UUDDDDU": 942,
        "DDDUUUD": 854,
        "DDDUUDD": 821,
        "DDDUDDD": 814,
        "UDDDDUU": 806,
        "DRDRDRD": 789,
        "DDUUDDD": 775
    },
    "8": {
        "UUUDDDDD": 657,
        "UUUUDDDD": 583,
        "DDDUUUDD": 573,
        "DUUUDDDD": 570,
        "DDDDUUUU": 549,
        "DDUUUDDD": 520,
        "DDDUUDDD": 494,
        "DDDDDUUU": 493,
        "DDUUUUDD": 469,
        "UUUDDDDU": 464,
        "UDDDDUUU": 456,
        "DDDUUUUU": 453,
        "UUUUUDDD": 453,
        "DDUDDUDD": 448,
        "DRDRDRDR": 422
    },
    "9": {
        "UUUUDDDDD": 320,
        "DDDUUUDDD": 310,
        "UDDUDDUDD": 289,
        "DDUUUDDDD": 277,
        "DDDDDUUUU": 267,
        "DDDUUUUDD": 266,
        "UUUUUDDDD": 261,
        "DDDDUUUUU": 256,
        "DUDDUDDUD": 249,
        "DDDDDDUUU": 248,
        "UUUDDDDUD": 247,
        "DDDDUUUDD": 245,
        "UUUDDDDDD": 245,
        "UDDDUUUDD": 240,
        "DDUUUUDDD": 238
    },
    "10": {
        "DUDDUDDUDD": 168,
        "DDDUUUDDDD": 166,
        "DDDDUUUUDD": 163,
        "UUUUUDDDDD": 163,
        "DDDDDDUUUU": 160,
        "UDDUDDUDDU": 147,
        "DDUUUUDDDD": 144,
        "DDUDDUDDUD": 144,
        "DDDDUUUDDD": 143,
        "DDDDDUUUUU": 140,
        "UUUUDDRDRD": 140,
        "DDDUUUUDDD": 140,
        "DDDDDWDDDD": 138,
        "UUUDDRDRDR": 136,
        "UUDDDUUDDD": 136
    },
    "11": {
        "DDUDDUDDUDD": 110,
        "DDDDUUUUDDD": 105,
        "UUUUDDRDRDR": 97,
        "UDDUDDUDDUD": 93,
        "DDDDUUUDDDD": 89,
        "UUDDDDUUUDD": 82,
        "DDDDDDUUUUU": 82,
        "DUDDUDDUDDU": 82,
        "DRDRDRDRDRD": 81,
        "RDRDRDRDRDR": 81,
        "DDDDDUUUUDD": 81,
        "DDDUUUUDDDD": 79,
        "DDDDDDDUUUU": 78,
        "DDDDUUUUUDD": 76,
        "DDUUUUUDDDD": 75
    },
    "12": {
        "UDDUDDUDDUDD": 71,
        "DDDDUUUUDDDD": 63,
        "DDUUUUDDRDRD": 57,
        "RDUUDDRDUUDD": 57,
        "DUDDUDDUDDUD": 57,
        "DRDRDRDRDRDR": 56,
        "DDDDDDUUUUDD": 55,
        "DDUUUUUDDDDD": 51,
        "UUUUUDDRDRDR": 51,
        "UUDDDDUUUDDD": 50,
        "DDUDDUDDUDDU": 50,
        "DDDUUUUDDRDR": 47,
        "UDDDDDDUUUUU": 47,
        "DDDDDUUUUDDD": 47,
        "UUUDDDDDWDDD": 47
    },
    "13": {
        "DUDDUDDUDDUDD": 46,
        "DUUDDRDUUDDRD": 42,
        "DRDUUDDRDUUDD": 39,
        "RDUUDDRDUUDDR": 38,
        "DDUUUUDDRDRDR": 37,
        "DDDDUUUUDDDDD": 37,
        "DDUDDUDDUDDUD": 37,
        "UDDUDDUDDUDDU": 36,
        "DUUUUUDDRDRDR": 35,
        "DDDUUUUDDRDRD": 35,
        "DDRDUUDDRDUUD": 35,
        "UDDRDUUDDRDUU": 35,
        "DDDDDUUUUDDDD": 35,
        "DDDDDDDUUUUDD": 34,
        "UUUDDDDDWDDDD": 33
    },
    "14": {
        "RDUUDDRDUUDDRD": 38,
        "DDRDUUDDRDUUDD": 35,
        "UDDRDUUDDRDUUD": 32,
        "DDUUUUUDDRDRDR": 30,
        "UUDDRDUUDDRDUU": 30,
        "DUUDDRDUUDDRDU": 30,
        "DDDUUUUUDDRDRD": 29,
        "DRDRWUDDDRDUUU": 28,
        "DDDRDUUUDRDRWU": 27,
        "UDDDRDUUUDRDRW": 27,
        "UDDUDDUDDUDDUD": 27,
        "DDUDDUDDUDDUDD": 27,
        "UDRDRWUDDDRDUU": 25,
        "UUDRDRWUDDDRDU": 25,
        "UUUDRDRWUDDDRD": 25
    }
}